[{"name":"Eclipse","price":55,"href":"http://google.cn"},
{"name":"Pathfinder","price":15,"href":"https://wikimedia.org"},
{"name":"riolet","price":58,"href":"http://kickstarter.com"},
{"name":"Taurus X","price":10,"href":"https://theglobeandmail.com"},
{"name":"Grand Prix","price":31,"href":"http://princeton.edu"},
{"name":"Silhouette","price":29,"href":"http://pinterest.com"},
{"name":"Expo","price":46,"href":"https://pen.io"},
{"name":"900","price":66,"href":"https://psu.edu"},
{"name":"525","price":13,"href":"http://example.com"},
{"name":"Prowler","price":70,"href":"http://earthlink.net"},
{"name":"S-Series","price":95,"href":"http://toplist.cz"},
{"name":"RS 4","price":94,"href":"http://upenn.edu"},
{"name":"Excursion","price":31,"href":"https://seesaa.net"},
{"name":"A8","price":67,"href":"http://t-online.de"},
{"name":"Mountaineer","price":82,"href":"https://about.com"},
{"name":"90","price":75,"href":"http://webeden.co.uk"},
{"name":"Aerio","price":56,"href":"http://bloomberg.com"},
{"name":"300C","price":40,"href":"https://google.ca"},
{"name":"Prizm","price":51,"href":"http://microsoft.com"},
{"name":"B-Series","price":47,"href":"http://cocolog-nifty.com"},
{"name":"Sunbird","price":85,"href":"https://spotify.com"},
{"name":"LX","price":38,"href":"http://google.com.hk"},
{"name":"Bonneville","price":62,"href":"https://dmoz.org"},
{"name":"Grand Voyager","price":98,"href":"http://adobe.com"},
{"name":"Suburban 2500","price":29,"href":"https://berkeley.edu"},
{"name":"Grand Prix","price":35,"href":"https://usatoday.com"},
{"name":"Corvette","price":95,"href":"https://jiathis.com"},
{"name":"Concorde","price":89,"href":"http://sun.com"},
{"name":"Continental Flying Spur","price":33,"href":"https://statcounter.com"},
{"name":"XK Series","price":60,"href":"http://si.edu"},
{"name":"Pathfinder","price":71,"href":"http://vistaprint.com"},
{"name":"6 Series","price":37,"href":"https://jalbum.net"},
{"name":"Jetta","price":78,"href":"https://google.ru"},
{"name":"S4","price":72,"href":"http://tinyurl.com"},
{"name":"Ram Van 1500","price":60,"href":"https://ocn.ne.jp"},
{"name":"Escalade EXT","price":51,"href":"http://biglobe.ne.jp"},
{"name":"DeVille","price":88,"href":"https://nih.gov"},
{"name":"Town Car","price":25,"href":"https://blogspot.com"},
{"name":"Jetta III","price":74,"href":"http://jigsy.com"},
{"name":"S6","price":30,"href":"http://boston.com"},
{"name":"C-Class","price":95,"href":"http://msu.edu"},
{"name":"Discovery Series II","price":43,"href":"http://netvibes.com"},
{"name":"Spirit","price":37,"href":"https://fda.gov"},
{"name":"Monterey","price":94,"href":"http://vinaora.com"},
{"name":"Camaro","price":22,"href":"https://abc.net.au"},
{"name":"Safari","price":76,"href":"http://hugedomains.com"},
{"name":"Maxima","price":75,"href":"https://prlog.org"},
{"name":"Explorer Sport Trac","price":88,"href":"https://sciencedaily.com"},
{"name":"Range Rover","price":85,"href":"http://salon.com"},
{"name":"Xtra","price":90,"href":"http://shinystat.com"},
{"name":"Eos","price":95,"href":"http://usatoday.com"},
{"name":"Colorado","price":49,"href":"http://businessweek.com"},
{"name":"Camaro","price":68,"href":"https://dell.com"},
{"name":"Sky","price":59,"href":"https://altervista.org"},
{"name":"6 Series","price":77,"href":"https://nih.gov"},
{"name":"Explorer","price":57,"href":"http://hatena.ne.jp"},
{"name":"XC60","price":21,"href":"https://cbsnews.com"},
{"name":"Sonoma","price":91,"href":"https://skype.com"},
{"name":"Sunbird","price":26,"href":"http://nsw.gov.au"},
{"name":"626","price":57,"href":"http://constantcontact.com"},
{"name":"A3","price":24,"href":"https://unicef.org"},
{"name":"3500","price":84,"href":"https://msn.com"},
{"name":"Caravan","price":35,"href":"https://linkedin.com"},
{"name":"4Runner","price":34,"href":"http://google.fr"},
{"name":"IS-F","price":87,"href":"http://networksolutions.com"},
{"name":"PT Cruiser","price":35,"href":"http://wired.com"},
{"name":"Ram 1500","price":72,"href":"https://delicious.com"},
{"name":"Jimmy","price":79,"href":"https://army.mil"},
{"name":"2e","price":10,"href":"http://chronoengine.com"},
{"name":"Prius","price":41,"href":"http://gmpg.org"},
{"name":"R32","price":85,"href":"http://infoseek.co.jp"},
{"name":"Tracer","price":42,"href":"https://businesswire.com"},
{"name":"Yukon","price":34,"href":"http://weather.com"},
{"name":"Previa","price":93,"href":"https://wisc.edu"},
{"name":"9-3","price":30,"href":"http://51.la"},
{"name":"Breeze","price":79,"href":"http://disqus.com"},
{"name":"Beretta","price":72,"href":"https://tinypic.com"},
{"name":"Gemini","price":40,"href":"https://arizona.edu"},
{"name":"Ram 2500","price":78,"href":"https://nationalgeographic.com"},
{"name":"Neon","price":62,"href":"http://cdbaby.com"},
{"name":"Firefly","price":92,"href":"http://irs.gov"},
{"name":"Pajero","price":18,"href":"https://ucoz.com"},
{"name":"Grand Prix","price":86,"href":"http://1688.com"},
{"name":"X6","price":12,"href":"http://earthlink.net"},
{"name":"G-Series 2500","price":14,"href":"https://ihg.com"},
{"name":"Accord","price":65,"href":"http://shop-pro.jp"},
{"name":"2CV","price":74,"href":"https://tamu.edu"},
{"name":"Vigor","price":37,"href":"https://nature.com"},
{"name":"Sunfire","price":32,"href":"http://theguardian.com"},
{"name":"Rally Wagon 3500","price":13,"href":"http://google.de"},
{"name":"Vision","price":96,"href":"http://discuz.net"},
{"name":"Milan","price":73,"href":"http://wisc.edu"},
{"name":"LeSabre","price":54,"href":"http://myspace.com"},
{"name":"Grand Prix","price":71,"href":"https://si.edu"},
{"name":"Metro","price":28,"href":"https://facebook.com"},
{"name":"Monterey","price":46,"href":"http://ning.com"},
{"name":"F250","price":20,"href":"https://exblog.jp"},
{"name":"Tracker","price":97,"href":"http://thetimes.co.uk"},
{"name":"Grand Caravan","price":68,"href":"http://ehow.com"},
{"name":"Traverse","price":85,"href":"http://weebly.com"},
{"name":"XJ","price":13,"href":"http://imageshack.us"},
{"name":"B-Series Plus","price":71,"href":"https://europa.eu"},
{"name":"S40","price":84,"href":"http://barnesandnoble.com"},
{"name":"Town Car","price":34,"href":"http://goo.gl"},
{"name":"Sebring","price":62,"href":"http://yolasite.com"},
{"name":"Montero","price":48,"href":"http://tmall.com"},
{"name":"Ram Van 3500","price":42,"href":"http://sphinn.com"},
{"name":"Coupe Quattro","price":80,"href":"https://ebay.co.uk"},
{"name":"Cordia","price":13,"href":"http://berkeley.edu"},
{"name":"Mini","price":13,"href":"http://surveymonkey.com"},
{"name":"Firefly","price":54,"href":"http://comcast.net"},
{"name":"Th!nk","price":94,"href":"https://jimdo.com"},
{"name":"GTI","price":52,"href":"https://soundcloud.com"},
{"name":"Suburban 1500","price":29,"href":"http://ted.com"},
{"name":"F-Series","price":91,"href":"https://bravesites.com"},
{"name":"MDX","price":80,"href":"http://amazon.co.uk"},
{"name":"Suburban 2500","price":50,"href":"http://marketwatch.com"},
{"name":"LeSabre","price":64,"href":"http://imdb.com"},
{"name":"Bronco","price":79,"href":"http://bbc.co.uk"},
{"name":"Entourage","price":100,"href":"http://dell.com"},
{"name":"612 Scaglietti","price":85,"href":"http://webeden.co.uk"},
{"name":"Grand Vitara","price":33,"href":"https://reference.com"},
{"name":"Discovery","price":60,"href":"https://opera.com"},
{"name":"EXP","price":82,"href":"http://woothemes.com"},
{"name":"CT","price":93,"href":"https://narod.ru"},
{"name":"Ranger","price":73,"href":"https://npr.org"},
{"name":"Yukon XL 2500","price":98,"href":"http://nydailynews.com"},
{"name":"Express","price":44,"href":"https://cisco.com"},
{"name":"Colt","price":38,"href":"https://jalbum.net"},
{"name":"Regal","price":57,"href":"https://fotki.com"},
{"name":"Xtra","price":74,"href":"http://marketwatch.com"},
{"name":"RS 6","price":24,"href":"http://liveinternet.ru"},
{"name":"Ram Van 2500","price":98,"href":"https://fc2.com"},
{"name":"Discovery Series II","price":35,"href":"http://timesonline.co.uk"},
{"name":"MX-5","price":78,"href":"http://reference.com"},
{"name":"H1","price":32,"href":"http://who.int"},
{"name":"Escort","price":91,"href":"http://wikimedia.org"},
{"name":"Mustang","price":56,"href":"https://sbwire.com"},
{"name":"57","price":29,"href":"http://youku.com"},
{"name":"Catera","price":96,"href":"https://twitpic.com"},
{"name":"5 Series","price":14,"href":"https://jiathis.com"},
{"name":"MX-6","price":32,"href":"https://dell.com"},
{"name":"D250","price":81,"href":"http://mit.edu"},
{"name":"Escalade EXT","price":59,"href":"http://google.fr"},
{"name":"Lanos","price":78,"href":"http://phoca.cz"},
{"name":"Civic","price":84,"href":"https://geocities.jp"},
{"name":"Swift","price":76,"href":"https://fotki.com"},
{"name":"MKX","price":44,"href":"http://gmpg.org"},
{"name":"Tempo","price":51,"href":"http://statcounter.com"},
{"name":"88","price":77,"href":"https://purevolume.com"},
{"name":"Grand Prix","price":59,"href":"http://biblegateway.com"},
{"name":"Tacoma","price":22,"href":"http://ehow.com"},
{"name":"Charger","price":29,"href":"https://storify.com"},
{"name":"911","price":12,"href":"https://youtu.be"},
{"name":"Stylus","price":77,"href":"https://icio.us"},
{"name":"Uplander","price":37,"href":"https://nhs.uk"},
{"name":"S60","price":54,"href":"https://ocn.ne.jp"},
{"name":"Yukon XL 1500","price":44,"href":"http://domainmarket.com"},
{"name":"F250","price":45,"href":"https://harvard.edu"},
{"name":"Tracer","price":52,"href":"http://fc2.com"},
{"name":"Continental","price":58,"href":"https://fema.gov"},
{"name":"PT Cruiser","price":24,"href":"http://indiatimes.com"},
{"name":"Gallardo","price":96,"href":"http://unicef.org"},
{"name":"Cayenne","price":16,"href":"http://berkeley.edu"},
{"name":"Sonata","price":90,"href":"http://ustream.tv"},
{"name":"Yukon","price":30,"href":"http://360.cn"},
{"name":"Endeavor","price":50,"href":"http://un.org"},
{"name":"F-Series","price":82,"href":"http://loc.gov"},
{"name":"Tiburon","price":82,"href":"https://disqus.com"},
{"name":"B-Series Plus","price":41,"href":"http://nytimes.com"},
{"name":"Th!nk","price":22,"href":"https://sciencedaily.com"},
{"name":"Civic","price":14,"href":"https://guardian.co.uk"},
{"name":"Gemini","price":96,"href":"http://odnoklassniki.ru"},
{"name":"I","price":84,"href":"http://ask.com"},
{"name":"Aztek","price":70,"href":"https://cpanel.net"},
{"name":"550","price":12,"href":"http://i2i.jp"},
{"name":"Savana 2500","price":71,"href":"https://irs.gov"},
{"name":"S-Series","price":35,"href":"https://symantec.com"},
{"name":"Ram Wagon B150","price":59,"href":"https://cafepress.com"},
{"name":"Somerset","price":56,"href":"http://123-reg.co.uk"},
{"name":"Monte Carlo","price":18,"href":"https://theatlantic.com"},
{"name":"Ram Van 1500","price":52,"href":"http://nbcnews.com"},
{"name":"Escalade ESV","price":87,"href":"https://technorati.com"},
{"name":"Villager","price":16,"href":"http://wisc.edu"},
{"name":"Civic","price":27,"href":"https://wiley.com"},
{"name":"W201","price":38,"href":"https://squarespace.com"},
{"name":"Equinox","price":43,"href":"http://nps.gov"},
{"name":"Econoline E350","price":31,"href":"http://last.fm"},
{"name":"Elise","price":28,"href":"https://vimeo.com"},
{"name":"7 Series","price":11,"href":"https://csmonitor.com"},
{"name":"Murciélago","price":23,"href":"http://nhs.uk"},
{"name":"RL","price":72,"href":"https://oaic.gov.au"},
{"name":"V70","price":78,"href":"https://livejournal.com"},
{"name":"Diablo","price":66,"href":"https://infoseek.co.jp"},
{"name":"New Beetle","price":39,"href":"http://altervista.org"},
{"name":"900","price":24,"href":"http://netscape.com"},
{"name":"Explorer Sport Trac","price":69,"href":"http://vinaora.com"},
{"name":"Mirage","price":70,"href":"http://reverbnation.com"},
{"name":"Grand Caravan","price":79,"href":"https://gmpg.org"},
{"name":"Sonoma","price":39,"href":"https://1688.com"},
{"name":"Ram 1500 Club","price":68,"href":"https://a8.net"},
{"name":"Continental","price":96,"href":"http://goo.gl"},
{"name":"Rally Wagon 1500","price":100,"href":"https://com.com"},
{"name":"LR4","price":17,"href":"http://msn.com"},
{"name":"Pilot","price":88,"href":"https://eepurl.com"},
{"name":"M3","price":11,"href":"http://state.tx.us"},
{"name":"APV","price":76,"href":"https://scientificamerican.com"},
{"name":"300SD","price":72,"href":"https://macromedia.com"},
{"name":"Gemini","price":33,"href":"https://usgs.gov"},
{"name":"Discovery","price":81,"href":"http://woothemes.com"},
{"name":"Prius","price":81,"href":"http://kickstarter.com"},
{"name":"Passat","price":37,"href":"http://moonfruit.com"},
{"name":"Ram 2500 Club","price":89,"href":"https://nydailynews.com"},
{"name":"Caravan","price":79,"href":"http://cpanel.net"},
{"name":"Firebird Formula","price":43,"href":"http://clickbank.net"},
{"name":"XL-7","price":38,"href":"http://apache.org"},
{"name":"Outback","price":39,"href":"https://ovh.net"},
{"name":"CX","price":28,"href":"http://state.tx.us"},
{"name":"XL-7","price":94,"href":"https://hao123.com"},
{"name":"A3","price":60,"href":"http://usatoday.com"},
{"name":"Express 2500","price":81,"href":"http://cnet.com"},
{"name":"TT","price":44,"href":"https://ycombinator.com"},
{"name":"Concorde","price":65,"href":"https://reddit.com"},
{"name":"Camaro","price":74,"href":"https://livejournal.com"},
{"name":"Legend","price":83,"href":"https://slashdot.org"},
{"name":"Scoupe","price":12,"href":"https://lulu.com"},
{"name":"960","price":19,"href":"http://hatena.ne.jp"},
{"name":"rio","price":81,"href":"https://wunderground.com"},
{"name":"Dakota Club","price":68,"href":"https://wix.com"},
{"name":"Esteem","price":13,"href":"https://naver.com"},
{"name":"C30","price":91,"href":"http://theatlantic.com"},
{"name":"Escalade ESV","price":72,"href":"https://wired.com"},
{"name":"GTI","price":50,"href":"http://lycos.com"},
{"name":"Sportage","price":22,"href":"http://quantcast.com"},
{"name":"EX","price":82,"href":"http://usatoday.com"},
{"name":"MX-3","price":42,"href":"https://washingtonpost.com"},
{"name":"Discovery","price":87,"href":"https://mlb.com"},
{"name":"CL-Class","price":28,"href":"http://huffingtonpost.com"},
{"name":"Corrado","price":49,"href":"https://woothemes.com"},
{"name":"Passat","price":59,"href":"http://huffingtonpost.com"},
{"name":"V70","price":92,"href":"https://google.de"},
{"name":"Q5","price":57,"href":"http://hibu.com"},
{"name":"Monterey","price":34,"href":"http://oracle.com"},
{"name":"300SE","price":94,"href":"https://woothemes.com"},
{"name":"Sierra 2500","price":41,"href":"https://liveinternet.ru"},
{"name":"Optima","price":18,"href":"https://mayoclinic.com"},
{"name":"xB","price":59,"href":"http://mapy.cz"},
{"name":"Q","price":46,"href":"http://flavors.me"},
{"name":"XR4Ti","price":84,"href":"http://howstuffworks.com"},
{"name":"Caravan","price":14,"href":"http://acquirethisname.com"},
{"name":"MX-3","price":38,"href":"https://eventbrite.com"},
{"name":"Titan","price":85,"href":"https://bravesites.com"},
{"name":"Intrepid","price":76,"href":"http://smh.com.au"},
{"name":"850","price":22,"href":"http://usnews.com"},
{"name":"Mountaineer","price":45,"href":"https://dagondesign.com"},
{"name":"Jetta","price":19,"href":"http://cbc.ca"},
{"name":"Ascender","price":63,"href":"https://jiathis.com"},
{"name":"Mini Cooper","price":14,"href":"https://youku.com"},
{"name":"Discovery Series II","price":21,"href":"https://hao123.com"},
{"name":"Ram 3500","price":92,"href":"https://wp.com"},
{"name":"Civic","price":36,"href":"http://yelp.com"},
{"name":"Gallardo","price":19,"href":"http://opera.com"},
{"name":"900","price":48,"href":"https://epa.gov"},
{"name":"C70","price":74,"href":"http://thetimes.co.uk"},
{"name":"Bravada","price":99,"href":"http://ycombinator.com"},
{"name":"Altima","price":24,"href":"https://statcounter.com"},
{"name":"Sportage","price":54,"href":"http://bloomberg.com"},
{"name":"300","price":67,"href":"http://symantec.com"},
{"name":"Odyssey","price":13,"href":"https://alexa.com"},
{"name":"Grand Marquis","price":39,"href":"http://livejournal.com"},
{"name":"B-Series","price":81,"href":"http://goo.gl"},
{"name":"SL-Class","price":13,"href":"https://biglobe.ne.jp"},
{"name":"Trooper","price":87,"href":"http://youtube.com"},
{"name":"Aveo","price":34,"href":"https://admin.ch"},
{"name":"Seville","price":23,"href":"http://lulu.com"},
{"name":"Supra","price":76,"href":"http://msu.edu"},
{"name":"RX","price":67,"href":"https://paypal.com"},
{"name":"LaCrosse","price":79,"href":"https://census.gov"},
{"name":"G-Series G30","price":82,"href":"https://sfgate.com"},
{"name":"Savana 2500","price":51,"href":"https://google.co.uk"},
{"name":"F250","price":45,"href":"http://usda.gov"},
{"name":"XF","price":98,"href":"http://wunderground.com"},
{"name":"Courier","price":12,"href":"http://mozilla.org"},
{"name":"Town & Country","price":49,"href":"https://marriott.com"},
{"name":"Discovery Series II","price":68,"href":"https://yolasite.com"},
{"name":"Excel","price":83,"href":"https://bbb.org"},
{"name":"Dakota","price":86,"href":"http://webmd.com"},
{"name":"Truck","price":49,"href":"http://mediafire.com"},
{"name":"Stratus","price":95,"href":"https://delicious.com"},
{"name":"1 Series","price":30,"href":"http://cbc.ca"},
{"name":"G","price":93,"href":"https://msn.com"},
{"name":"Yukon","price":10,"href":"https://gmpg.org"},
{"name":"Yukon XL 2500","price":14,"href":"http://sciencedirect.com"},
{"name":"CX-7","price":18,"href":"https://paypal.com"},
{"name":"Ram Van 2500","price":74,"href":"https://dot.gov"},
{"name":"Lancer","price":80,"href":"https://narod.ru"},
{"name":"Reatta","price":27,"href":"https://bizjournals.com"},
{"name":"Leganza","price":70,"href":"http://vistaprint.com"},
{"name":"TSX","price":95,"href":"http://hibu.com"},
{"name":"T100","price":95,"href":"http://ihg.com"},
{"name":"Taurus","price":37,"href":"https://amazon.com"},
{"name":"Sierra 1500","price":74,"href":"http://hao123.com"},
{"name":"Z4 M","price":30,"href":"https://creativecommons.org"},
{"name":"S4","price":45,"href":"http://godaddy.com"},
{"name":"Dakota","price":66,"href":"https://spiegel.de"},
{"name":"S80","price":11,"href":"http://economist.com"},
{"name":"RX-7","price":85,"href":"http://indiatimes.com"},
{"name":"Intrepid","price":52,"href":"http://harvard.edu"},
{"name":"Eldorado","price":83,"href":"https://issuu.com"},
{"name":"F250","price":33,"href":"http://noaa.gov"},
{"name":"Fit","price":73,"href":"http://sogou.com"},
{"name":"Bronco","price":75,"href":"http://va.gov"},
{"name":"STS","price":55,"href":"https://myspace.com"},
{"name":"Element","price":10,"href":"https://geocities.com"},
{"name":"Quattroporte","price":96,"href":"https://discuz.net"},
{"name":"LS","price":34,"href":"https://wp.com"},
{"name":"MP4-12C","price":99,"href":"http://photobucket.com"},
{"name":"Diablo","price":20,"href":"https://jimdo.com"},
{"name":"Type-1h","price":31,"href":"https://java.com"},
{"name":"EXP","price":81,"href":"http://cdbaby.com"},
{"name":"Familia","price":46,"href":"https://theatlantic.com"},
{"name":"CL","price":25,"href":"https://sbwire.com"},
{"name":"240","price":30,"href":"https://usnews.com"},
{"name":"Sierra 1500","price":37,"href":"https://jigsy.com"},
{"name":"A3","price":56,"href":"https://time.com"},
{"name":"3500","price":79,"href":"http://51.la"},
{"name":"Caprice","price":49,"href":"http://salon.com"},
{"name":"M3","price":46,"href":"http://newyorker.com"},
{"name":"CLS-Class","price":46,"href":"https://csmonitor.com"},
{"name":"Legacy","price":44,"href":"https://tumblr.com"},
{"name":"Vibe","price":72,"href":"http://multiply.com"},
{"name":"Prius","price":92,"href":"https://mysql.com"},
{"name":"Taurus","price":16,"href":"http://narod.ru"},
{"name":"9-2X","price":39,"href":"http://zdnet.com"},
{"name":"5 Series","price":29,"href":"http://bloglovin.com"},
{"name":"HHR","price":99,"href":"https://surveymonkey.com"},
{"name":"Tredia","price":78,"href":"http://360.cn"},
{"name":"F350","price":18,"href":"http://vkontakte.ru"},
{"name":"Laser","price":71,"href":"http://nih.gov"},
{"name":"Fit","price":39,"href":"http://independent.co.uk"},
{"name":"Altima","price":85,"href":"https://dropbox.com"},
{"name":"Silverado 3500","price":96,"href":"https://reuters.com"},
{"name":"Canyon","price":67,"href":"https://facebook.com"},
{"name":"Sierra 2500","price":62,"href":"https://cocolog-nifty.com"},
{"name":"Mustang","price":17,"href":"http://shutterfly.com"},
{"name":"S40","price":63,"href":"https://chicagotribune.com"},
{"name":"Explorer Sport","price":65,"href":"http://utexas.edu"},
{"name":"Mini","price":62,"href":"https://umich.edu"},
{"name":"IS","price":13,"href":"http://instagram.com"},
{"name":"Montero","price":50,"href":"https://hubpages.com"},
{"name":"100","price":25,"href":"http://pcworld.com"},
{"name":"Legacy","price":71,"href":"https://twitter.com"},
{"name":"Tempo","price":81,"href":"http://dropbox.com"},
{"name":"Jetta","price":69,"href":"http://reuters.com"},
{"name":"C-MAX Hybrid","price":99,"href":"http://slideshare.net"},
{"name":"Explorer","price":72,"href":"http://vimeo.com"},
{"name":"F350","price":49,"href":"http://woothemes.com"},
{"name":"G25","price":100,"href":"http://fotki.com"},
{"name":"Azure","price":64,"href":"https://webeden.co.uk"},
{"name":"Tacoma Xtra","price":60,"href":"https://360.cn"},
{"name":"F250","price":88,"href":"https://google.ru"},
{"name":"Camry","price":46,"href":"http://squidoo.com"},
{"name":"Cougar","price":74,"href":"http://vkontakte.ru"},
{"name":"Maxima","price":47,"href":"http://issuu.com"},
{"name":"PT Cruiser","price":23,"href":"https://usnews.com"},
{"name":"GranTurismo","price":33,"href":"http://virginia.edu"},
{"name":"Tercel","price":43,"href":"https://nationalgeographic.com"},
{"name":"Ram 1500","price":73,"href":"https://goo.gl"},
{"name":"Avalon","price":51,"href":"https://nps.gov"},
{"name":"XLR","price":60,"href":"http://newyorker.com"},
{"name":"Express 3500","price":13,"href":"http://posterous.com"},
{"name":"SC","price":98,"href":"https://java.com"},
{"name":"Sonoma","price":66,"href":"http://webeden.co.uk"},
{"name":"Hombre","price":34,"href":"http://goo.gl"},
{"name":"240SX","price":90,"href":"http://thetimes.co.uk"},
{"name":"Prizm","price":19,"href":"https://ebay.com"},
{"name":"Explorer","price":25,"href":"https://typepad.com"},
{"name":"Forester","price":45,"href":"http://omniture.com"},
{"name":"RX-8","price":72,"href":"http://nifty.com"},
{"name":"Continental Flying Spur","price":29,"href":"https://aboutads.info"},
{"name":"F-Series Super Duty","price":34,"href":"http://fema.gov"},
{"name":"SJ","price":25,"href":"https://phoca.cz"},
{"name":"XJ Series","price":99,"href":"https://noaa.gov"},
{"name":"Regal","price":40,"href":"http://cafepress.com"},
{"name":"Camaro","price":53,"href":"https://bluehost.com"},
{"name":"Civic","price":50,"href":"http://smugmug.com"},
{"name":"Navigator","price":47,"href":"http://addtoany.com"},
{"name":"Outlander","price":91,"href":"https://linkedin.com"},
{"name":"Firefly","price":80,"href":"https://123-reg.co.uk"},
{"name":"Prizm","price":88,"href":"https://elegantthemes.com"},
{"name":"B-Series","price":45,"href":"http://forbes.com"},
{"name":"Transit Connect","price":48,"href":"http://zdnet.com"},
{"name":"Defender 110","price":92,"href":"http://admin.ch"},
{"name":"S2000","price":18,"href":"https://instagram.com"},
{"name":"SL-Class","price":45,"href":"http://livejournal.com"},
{"name":"Armada","price":30,"href":"https://myspace.com"},
{"name":"SC","price":69,"href":"https://miibeian.gov.cn"},
{"name":"Accord Crosstour","price":74,"href":"http://icio.us"},
{"name":"Rodeo","price":42,"href":"https://is.gd"},
{"name":"Forester","price":52,"href":"http://yahoo.co.jp"},
{"name":"Prowler","price":94,"href":"https://constantcontact.com"},
{"name":"Sienna","price":51,"href":"http://bing.com"},
{"name":"Savana","price":50,"href":"https://bing.com"},
{"name":"Cougar","price":43,"href":"http://admin.ch"},
{"name":"Miata MX-5","price":17,"href":"https://mtv.com"},
{"name":"Express 2500","price":45,"href":"http://umich.edu"},
{"name":"164","price":77,"href":"http://tinypic.com"},
{"name":"Aerostar","price":73,"href":"http://utexas.edu"},
{"name":"Volare","price":91,"href":"https://ocn.ne.jp"},
{"name":"CR-V","price":47,"href":"https://cdbaby.com"},
{"name":"Cobalt","price":83,"href":"https://vkontakte.ru"},
{"name":"RL","price":36,"href":"http://mediafire.com"},
{"name":"Sidekick","price":78,"href":"http://sphinn.com"},
{"name":"Tahoe","price":66,"href":"https://berkeley.edu"},
{"name":"XK","price":96,"href":"http://amazon.co.uk"},
{"name":"Accent","price":40,"href":"https://boston.com"},
{"name":"Savana 2500","price":74,"href":"http://istockphoto.com"},
{"name":"Continental Mark VII","price":47,"href":"http://imgur.com"},
{"name":"G-Class","price":11,"href":"https://dmoz.org"},
{"name":"H1","price":89,"href":"http://twitpic.com"},
{"name":"M5","price":30,"href":"http://cbsnews.com"},
{"name":"M6","price":69,"href":"https://upenn.edu"},
{"name":"Altima","price":11,"href":"https://digg.com"},
{"name":"6 Series","price":93,"href":"https://seattletimes.com"},
{"name":"Town & Country","price":33,"href":"http://bloglines.com"},
{"name":"Mustang","price":92,"href":"https://hp.com"},
{"name":"Topaz","price":34,"href":"https://vk.com"},
{"name":"Sportage","price":92,"href":"https://admin.ch"},
{"name":"Mazda3","price":87,"href":"http://huffingtonpost.com"},
{"name":"Montero Sport","price":39,"href":"https://jimdo.com"},
{"name":"Galant","price":50,"href":"https://linkedin.com"},
{"name":"Magnum","price":14,"href":"https://histats.com"},
{"name":"Focus ST","price":89,"href":"https://ftc.gov"},
{"name":"Torrent","price":78,"href":"https://ihg.com"},
{"name":"Esprit","price":15,"href":"http://lycos.com"},
{"name":"Legacy","price":89,"href":"http://amazon.co.jp"},
{"name":"CX-5","price":20,"href":"http://marriott.com"},
{"name":"SL-Class","price":33,"href":"https://mlb.com"},
{"name":"S4","price":25,"href":"https://nba.com"},
{"name":"G-Series G10","price":64,"href":"http://yelp.com"},
{"name":"GTO","price":99,"href":"https://geocities.com"},
{"name":"Silverado 1500","price":18,"href":"https://lycos.com"},
{"name":"RSX","price":56,"href":"http://wiley.com"},
{"name":"IS F","price":29,"href":"https://kickstarter.com"},
{"name":"Mustang","price":60,"href":"https://ustream.tv"},
{"name":"TL","price":78,"href":"https://prnewswire.com"},
{"name":"GranTurismo","price":97,"href":"https://blogger.com"},
{"name":"Jimmy","price":92,"href":"http://goo.ne.jp"},
{"name":"Boxster","price":10,"href":"https://eepurl.com"},
{"name":"XL-7","price":25,"href":"https://livejournal.com"},
{"name":"F250","price":55,"href":"http://altervista.org"},
{"name":"J","price":53,"href":"http://miibeian.gov.cn"},
{"name":"Suburban 1500","price":77,"href":"http://imdb.com"},
{"name":"Silhouette","price":67,"href":"http://people.com.cn"},
{"name":"Spirit","price":61,"href":"http://dropbox.com"},
{"name":"XC90","price":99,"href":"https://opensource.org"},
{"name":"S-Class","price":23,"href":"https://1und1.de"},
{"name":"Golf","price":22,"href":"http://shop-pro.jp"},
{"name":"Range Rover","price":54,"href":"https://eventbrite.com"},
{"name":"D250","price":12,"href":"https://dmoz.org"},
{"name":"J","price":15,"href":"https://geocities.com"},
{"name":"Odyssey","price":81,"href":"https://aol.com"},
{"name":"C-Class","price":61,"href":"https://google.com.br"},
{"name":"Suburban 2500","price":31,"href":"http://umich.edu"},
{"name":"Sunfire","price":72,"href":"http://theglobeandmail.com"},
{"name":"Regal","price":72,"href":"https://t-online.de"},
{"name":"Bronco","price":90,"href":"https://istockphoto.com"},
{"name":"Express 2500","price":36,"href":"https://miibeian.gov.cn"},
{"name":"Lucerne","price":53,"href":"http://state.gov"},
{"name":"Pajero","price":33,"href":"https://ovh.net"},
{"name":"Tacoma","price":81,"href":"https://csmonitor.com"},
{"name":"NSX","price":48,"href":"http://soup.io"},
{"name":"Grand Prix","price":67,"href":"https://4shared.com"},
{"name":"QX","price":77,"href":"https://techcrunch.com"},
{"name":"LR2","price":88,"href":"https://hibu.com"},
{"name":"Spectra","price":68,"href":"http://google.co.uk"},
{"name":"Yukon Denali","price":34,"href":"http://narod.ru"},
{"name":"Sentra","price":78,"href":"https://blogspot.com"},
{"name":"Cougar","price":77,"href":"https://youtube.com"},
{"name":"Mustang","price":50,"href":"http://canalblog.com"},
{"name":"Integra","price":91,"href":"http://redcross.org"},
{"name":"Odyssey","price":16,"href":"http://multiply.com"},
{"name":"LeSabre","price":46,"href":"http://elegantthemes.com"},
{"name":"Fury","price":52,"href":"http://people.com.cn"},
{"name":"300","price":59,"href":"https://mozilla.com"},
{"name":"Sportage","price":22,"href":"https://sun.com"},
{"name":"Impreza","price":53,"href":"https://slate.com"},
{"name":"Windstar","price":49,"href":"https://oaic.gov.au"},
{"name":"Town & Country","price":33,"href":"http://google.es"},
{"name":"Econoline E350","price":82,"href":"http://blinklist.com"},
{"name":"164","price":44,"href":"http://infoseek.co.jp"},
{"name":"Highlander","price":20,"href":"http://arizona.edu"},
{"name":"Mustang","price":50,"href":"https://themeforest.net"},
{"name":"Sunfire","price":80,"href":"http://tinyurl.com"},
{"name":"Golf","price":15,"href":"https://vistaprint.com"},
{"name":"Xterra","price":14,"href":"https://netvibes.com"},
{"name":"Millenia","price":60,"href":"https://gov.uk"},
{"name":"Ridgeline","price":78,"href":"https://apple.com"},
{"name":"Silverado 3500","price":31,"href":"https://eepurl.com"},
{"name":"California","price":50,"href":"http://netlog.com"}]